fluent/__init__.py
fluent/syntax/__init__.py
fluent/syntax/ast.py
fluent/syntax/errors.py
fluent/syntax/ftlstream.py
fluent/syntax/parser.py
fluent/syntax/serializer.py
fluent/syntax/stream.py
fluent-0.7.0.dist-info/DESCRIPTION.rst
fluent-0.7.0.dist-info/METADATA
fluent-0.7.0.dist-info/RECORD
fluent-0.7.0.dist-info/WHEEL
fluent-0.7.0.dist-info/metadata.json
fluent-0.7.0.dist-info/top_level.txt
